<?xml version="1.0" encoding="utf-8" ?>
<dwsync>
<file name="readme.md" local="131429292765322480" remote="131429289200000000" testing="0" />
<file name="tinymce-small.eot" local="131429292765332505" remote="131429289200000000" testing="0" />
<file name="tinymce-small.json" local="131429292765342537" remote="131429289200000000" testing="0" />
<file name="tinymce-small.svg" local="131429292765352562" remote="131429289200000000" testing="0" />
<file name="tinymce-small.ttf" local="131429292765362594" remote="131429289200000000" testing="0" />
<file name="tinymce-small.woff" local="131429292765377626" remote="131429289200000000" testing="0" />
<file name="tinymce.eot" local="131429292765387650" remote="131429289200000000" testing="0" />
<file name="tinymce.json" local="131429292765407707" remote="131429289200000000" testing="0" />
<file name="tinymce.svg" local="131429292765422743" remote="131429289200000000" testing="0" />
<file name="tinymce.ttf" local="131429292765432775" remote="131429289200000000" testing="0" />
<file name="tinymce.woff" local="131429292765442800" remote="131429289200000000" testing="0" />
</dwsync>