<?xml version="1.0" encoding="utf-8" ?>
<dwsync>
<file name="404.php" local="131429292840642868" remote="131429289200000000" testing="0" />
<file name="archive.php" local="131429292840698018" remote="131429289200000000" testing="0" />
<file name="comments.php" local="131429292840703029" remote="131429289200000000" testing="0" />
<file name="content-author-box.php" local="131429292840713057" remote="131429289200000000" testing="0" />
<file name="content-header.php" local="131429292840723086" remote="131429289200000000" testing="0" />
<file name="content-large.php" local="131429292840763185" remote="131429289200000000" testing="0" />
<file name="content-loop.php" local="131429292840773228" remote="131429289200000000" testing="0" />
<file name="content-none.php" local="131429292840783242" remote="131429289200000000" testing="0" />
<file name="content-page.php" local="131429292840793270" remote="131429289200000000" testing="0" />
<file name="content-single.php" local="131429292840803295" remote="131429289200000000" testing="0" />
<file name="footer.php" local="131429292840948683" remote="131429289200000000" testing="0" />
<file name="functions.php" local="131429292840953697" remote="131429289200000000" testing="0" />
<file name="header.php" local="131429292840963726" remote="131429289200000000" testing="0" />
<file name="homepage.php" local="131429292840973747" remote="131429289200000000" testing="0" />
<file name="image.php" local="131429292840983779" remote="131429289200000000" testing="0" />
<file name="index.php" local="131429292841500148" remote="131429289200000000" testing="0" />
<file name="page.php" local="131429292842247137" remote="131429289200000000" testing="0" />
<file name="readme.txt" local="131429292842257165" remote="131429289200000000" testing="0" />
<file name="rtl.css" local="131429292842262176" remote="131429289200000000" testing="0" />
<file name="screenshot.png" local="131429292842317336" remote="131429289200000000" testing="0" />
<file name="search.php" local="131429292842327354" remote="131429289200000000" testing="0" />
<file name="sidebar.php" local="131429292842337375" remote="131429289200000000" testing="0" />
<file name="single.php" local="131429292842347400" remote="131429289200000000" testing="0" />
<file name="style.css" local="131429292842357432" remote="131429289200000000" testing="0" />
<file name="template-full.php" local="131429292842367457" remote="131429289200000000" testing="0" />
</dwsync>