<?xml version="1.0" encoding="utf-8" ?>
<dwsync>
<file name=".htaccess" local="131429293033897550" remote="131429289200000000" testing="0" />
<file name="canvas.html" local="131429293033912593" remote="131429289200000000" testing="0" />
<file name="herald.appcache" local="131429293034118145" remote="131429289200000000" testing="0" />
<file name="herald.appcacheOLD" local="131429293034158244" remote="131429289200000000" testing="0" />
<file name="index.html" local="131429293034544276" remote="131429289200000000" testing="0" />
<file name="offline.html" local="131429293036925607" remote="131429289200000000" testing="0" />
<file name="README.txt" local="131429293033902565" remote="131429289200000000" testing="0" />
<file name="register.html" local="131429293036935635" remote="131429289200000000" testing="0" />
</dwsync>